pyqudit/__init__.py
pyqudit/__main__.py
pyqudit/qudit.py
pyqudit-1.0.1.dist-info/DESCRIPTION.rst
pyqudit-1.0.1.dist-info/METADATA
pyqudit-1.0.1.dist-info/RECORD
pyqudit-1.0.1.dist-info/WHEEL
pyqudit-1.0.1.dist-info/entry_points.txt
pyqudit-1.0.1.dist-info/metadata.json
pyqudit-1.0.1.dist-info/top_level.txt
