Metadata-Version: 2.0
Name: pyqudit
Version: 1.0.1
Summary: Quantum Computing package. Use qudit gates and build simple N-D circuits.
Home-page: https://github.com/ordoptimus/pyqudit
Author: Ordoptimus, Rutuja343, kimyona-crypt
Author-email: orodaux@gmail.com
License: UNKNOWN
Project-URL: Bug Tracker, https://github.com/ordoptimus/pyqudit/issues
Platform: UNKNOWN
Classifier: Programming Language :: Python :: 3
Classifier: License :: OSI Approved :: MIT License
Classifier: Operating System :: OS Independent
Requires-Python: >=3.6
License-File: LICENSE
Requires-Dist: numpy
